cloning/__init__.py
cloning-0.0.0.dist-info/LICENSE.txt
cloning-0.0.0.dist-info/WHEEL
cloning-0.0.0.dist-info/METADATA
cloning-0.0.0.dist-info/RECORD
