Metadata-Version: 2.1
Name: cloning
Version: 0.0.0
Summary: Simulate DNA cloning reactions.
Author-email: Kale Kundert <kale@thekunderts.net>
Requires-Python: ~=3.7
Classifier: Programming Language :: Python :: 3
Requires-Dist: sphinx ; extra == "doc"
Requires-Dist: sphinx_rtd_theme ; extra == "doc"
Requires-Dist: autoclasstoc ; extra == "doc"
Requires-Dist: pytest ; extra == "test"
Requires-Dist: pytest-cov ; extra == "test"
Requires-Dist: parametrize_from_file ; extra == "test"
Requires-Dist: coveralls ; extra == "test"
Project-URL: Bug Tracker, https://github.com/kalekundert/cloning/issues
Project-URL: Continuous Integration, https://github.com/kalekundert/cloning/actions
Project-URL: Documentation, https://cloning.readthedocs.io/en/latest/
Project-URL: Test Coverage, https://coveralls.io/github/kalekundert/cloning
Project-URL: Version Control, https://github.com/kalekundert/cloning
Provides-Extra: doc
Provides-Extra: test
